openlm/__init__.py
openlm/llm/__init__.py
openlm/llm/base.py
openlm/llm/cohere.py
openlm/llm/huggingface.py
openlm/llm/openai.py
openlm/openlm.py
openlm-0.0.4.dist-info/LICENSE
openlm-0.0.4.dist-info/METADATA
openlm-0.0.4.dist-info/WHEEL
openlm-0.0.4.dist-info/RECORD
