Metadata-Version: 2.1
Name: openlm
Version: 0.0.4
Summary: Drop-in OpenAI-compatible that can call LLMs from other providers
License: MIT
Keywords: llm,ai,prompt,large language models,gpt-3,chatgpt
Author: Matt Rickard
Author-email: pypi@matt-rickard.com
Maintainer: Matt Rickard
Maintainer-email: pypi@matt-rickard.com
Requires-Python: >=3.8.1,<4.0
Classifier: Development Status :: 3 - Alpha
Classifier: Intended Audience :: Developers
Classifier: Intended Audience :: Science/Research
Classifier: License :: OSI Approved :: MIT License
Classifier: Programming Language :: Python :: 3
Classifier: Programming Language :: Python :: 3.9
Classifier: Programming Language :: Python :: 3.10
Classifier: Programming Language :: Python :: 3.11
Classifier: Programming Language :: Python :: 3
Classifier: Programming Language :: Python :: 3 :: Only
Classifier: Programming Language :: Python :: 3.7
Classifier: Programming Language :: Python :: 3.8
Classifier: Programming Language :: Python :: 3.9
Classifier: Topic :: Scientific/Engineering :: Artificial Intelligence
Classifier: Topic :: Software Development :: Libraries :: Python Modules
Classifier: Topic :: Text Processing :: Linguistic
Requires-Dist: requests (>=2,<3)
Project-URL: repository, https://github.com/r2d4/openlm
